{
    "INSTRUCTION": [
        {
            "ACTION": "SWIPE",
            "ACTIVE": [
                [
                    2,
                    5
                ],
                []
            ],
            "FLOOR": 1,
            "PLAYER": 0
        },
        {
            "ACTION": "GRAVITY",
            "ACTIVE": [
                [],
                [
                    1,
                    2,
                    5,
                    7
                ]
            ],
            "FLOOR": 2,
            "PLAYER": 1
        },
        {
            "ACTION": "SWIPE",
            "ACTIVE": null,
            "FLOOR": 3,
            "PLAYER": 1
        },
        {
            "ACTION": "SWIPE",
            "ACTIVE": [
                [
                    7,
                    9
                ],
                []
            ],
            "FLOOR": 4,
            "PLAYER": 0
        },
        {
            "ACTION": "VDP",
            "ACTIVE": [
                [
                    0
                ],
                [
                    9
                ]
            ],
            "FLOOR": 5,
            "PLAYER": 1
        }
    ],
    "NAME": "Nidhogg",
    "TEAM": [
        [
            {
                "+ATK": 99,
                "+HP": 66,
                "+RCV": 33,
                "AWAKE": 9,
                "ID": 4794,
                "LATENT": null,
                "LV": 99,
                "SLV": 0
            },
            {
                "+ATK": 0,
                "+HP": 0,
                "+RCV": 0,
                "AWAKE": 9,
                "ID": 5098,
                "LATENT": null,
                "LV": 99,
                "SLV": 0
            },
            {
                "+ATK": 99,
                "+HP": 99,
                "+RCV": 99,
                "AWAKE": 9,
                "ID": 4794,
                "LATENT": null,
                "LV": 99,
                "SLV": 0
            },
            null,
            {
                "+ATK": 0,
                "+HP": 0,
                "+RCV": 0,
                "AWAKE": 9,
                "ID": 2129,
                "LATENT": null,
                "LV": 99,
                "SLV": 0
            },
            {
                "+ATK": 0,
                "+HP": 0,
                "+RCV": 0,
                "AWAKE": 9,
                "ID": 4358,
                "LATENT": null,
                "LV": 99,
                "SLV": 0
            },
            {
                "+ATK": 0,
                "+HP": 0,
                "+RCV": 0,
                "AWAKE": 9,
                "ID": 4738,
                "LATENT": null,
                "LV": 99,
                "SLV": 0
            },
            {
                "+ATK": 0,
                "+HP": 0,
                "+RCV": 0,
                "AWAKE": 9,
                "ID": 2691,
                "LATENT": null,
                "LV": 99,
                "SLV": 0
            },
            {
                "+ATK": 0,
                "+HP": 0,
                "+RCV": 0,
                "AWAKE": 9,
                "ID": 4800,
                "LATENT": null,
                "LV": 99,
                "SLV": 0
            },
            {
                "+ATK": 0,
                "+HP": 0,
                "+RCV": 0,
                "AWAKE": 9,
                "ID": 3520,
                "LATENT": null,
                "LV": 99,
                "SLV": 0
            }
        ],
        [
            {
                "+ATK": 99,
                "+HP": 99,
                "+RCV": 99,
                "AWAKE": 6,
                "ID": 4691,
                "LATENT": null,
                "LV": 110,
                "SLV": 0
            },
            {
                "+ATK": 0,
                "+HP": 0,
                "+RCV": 0,
                "AWAKE": 9,
                "ID": 2691,
                "LATENT": null,
                "LV": 99,
                "SLV": 0
            },
            {
                "+ATK": 0,
                "+HP": 0,
                "+RCV": 0,
                "AWAKE": 9,
                "ID": 1923,
                "LATENT": null,
                "LV": 99,
                "SLV": 5
            },
            {
                "+ATK": 0,
                "+HP": 0,
                "+RCV": 0,
                "AWAKE": 9,
                "ID": 3338,
                "LATENT": null,
                "LV": 99,
                "SLV": 1
            },
            {
                "+ATK": 0,
                "+HP": 0,
                "+RCV": 0,
                "AWAKE": 9,
                "ID": 2129,
                "LATENT": null,
                "LV": 99,
                "SLV": 0
            },
            {
                "+ATK": 0,
                "+HP": 0,
                "+RCV": 0,
                "AWAKE": 9,
                "ID": 3903,
                "LATENT": null,
                "LV": 99,
                "SLV": 0
            },
            {
                "+ATK": 0,
                "+HP": 0,
                "+RCV": 0,
                "AWAKE": 9,
                "ID": 2129,
                "LATENT": null,
                "LV": 99,
                "SLV": 0
            },
            {
                "+ATK": 0,
                "+HP": 0,
                "+RCV": 0,
                "AWAKE": 9,
                "ID": 3903,
                "LATENT": null,
                "LV": 99,
                "SLV": 0
            },
            {
                "+ATK": 99,
                "+HP": 99,
                "+RCV": 99,
                "AWAKE": 9,
                "ID": 4736,
                "LATENT": [
                    7,
                    7,
                    7,
                    7,
                    7,
                    7,
                    7
                ],
                "LV": 99,
                "SLV": 0
            },
            {
                "+ATK": 0,
                "+HP": 0,
                "+RCV": 0,
                "AWAKE": 9,
                "ID": 3705,
                "LATENT": null,
                "LV": 99,
                "SLV": 0
            }
        ]
    ]
}